reorder_python_imports.py
reorder_python_imports_black-3.12.0.dist-info/LICENSE
reorder_python_imports_black-3.12.0.dist-info/METADATA
reorder_python_imports_black-3.12.0.dist-info/WHEEL
reorder_python_imports_black-3.12.0.dist-info/entry_points.txt
reorder_python_imports_black-3.12.0.dist-info/top_level.txt
reorder_python_imports_black-3.12.0.dist-info/RECORD
