Metadata-Version: 2.1
Name: reorder-python-imports-black
Version: 3.12.0
Summary: Tool for reordering python imports
Author-email: Anthony Sottile <asottile@umich.edu>, Wim Jeantine-Glenn <wim.glenn@gmail.com>
License: MIT
Project-URL: Upstream, https://github.com/asottile/reorder-python-imports
Project-URL: Homepage, https://github.com/wimglenn/reorder-python-imports-black
Classifier: License :: OSI Approved :: MIT License
Requires-Python: >=3.8
License-File: LICENSE
Requires-Dist: classify-imports >=4.1
